README.txt
setup.cfg
setup.py
rc/__init__.py
rc.policy.egg-info/PKG-INFO
rc.policy.egg-info/SOURCES.txt
rc.policy.egg-info/dependency_links.txt
rc.policy.egg-info/entry_points.txt
rc.policy.egg-info/namespace_packages.txt
rc.policy.egg-info/not-zip-safe
rc.policy.egg-info/paster_plugins.txt
rc.policy.egg-info/requires.txt
rc.policy.egg-info/top_level.txt
rc/policy/__init__.py
rc/policy/tests/__init__.py
rc/policy/tests/base.py
rc/policy/tests/test_setup.py