Metadata-Version: 1.0
Name: rc.policy
Version: 0.1adev
Summary: Policy for the RK
Home-page: http://svn.plone.org/svn/plone/plone.example
Author: inf
Author-email: inf@uni-trier.de
License: GPL
Keywords: rc redaktion sfb600
Platform: UNKNOWN
Classifier: Framework :: Plone
Classifier: Programming Language :: Python
Classifier: Topic :: Software Development :: Libraries :: Python Modules
